libmidi_io/__init__.py
libmidi_io/backends/__init__.py
libmidi_io/backends/alsamidi/__init__.py
libmidi_io/backends/fluidsynth/__init__.py
libmidi_io/backends/kdmapi/__init__.py
libmidi_io/backends/rtmidi/__init__.py
libmidi_io/types/__init__.py
libmidi_io/types/backend.py
libmidi_io/types/device.py
libmidi_io/types/port.py
libmidi_io/utils/__init__.py
libmidi_io/utils/lock.py
libmidi_io/utils/messages.py
libmidi_io/utils/sleep.py
libmidi_io-1.1.0.dist-info/METADATA
libmidi_io-1.1.0.dist-info/WHEEL
libmidi_io-1.1.0.dist-info/RECORD
