Metadata-Version: 2.3
Name: libmidi_io
Version: 1.1.0
Summary: MIDI I/O utils
License: LGPL-3.0-or-later
Author: Sebastiano Barezzi
Author-email: barezzisebastiano@gmail.com
Requires-Python: >=3.8,<4.0
Classifier: License :: OSI Approved :: GNU Lesser General Public License v3 or later (LGPLv3+)
Classifier: Programming Language :: Python :: 3
Classifier: Programming Language :: Python :: 3.8
Classifier: Programming Language :: Python :: 3.9
Classifier: Programming Language :: Python :: 3.10
Classifier: Programming Language :: Python :: 3.11
Classifier: Programming Language :: Python :: 3.12
Classifier: Programming Language :: Python :: 3.13
Requires-Dist: libmidi (>=1.1.0,<2.0.0)
Project-URL: Repository, https://github.com/python-midi/libmidi_io
